hatch_uvenv/__init__.py
hatch_uvenv/hooks.py
hatch_uvenv/plugin.py
hatch_uvenv/venv.py
hatch_uvenv-0.4.0.dist-info/METADATA
hatch_uvenv-0.4.0.dist-info/WHEEL
hatch_uvenv-0.4.0.dist-info/entry_points.txt
hatch_uvenv-0.4.0.dist-info/licenses/LICENSE
hatch_uvenv-0.4.0.dist-info/RECORD
