Metadata-Version: 2.4
Name: hatch-uvenv
Version: 0.4.0
Project-URL: Homepage, https://github.com/djcopley/hatch-uvenv
Project-URL: Repository, https://github.com/djcopley/hatch-uvenv.git
Project-URL: Issues, https://github.com/djcopley/hatch-uvenv/issues
Author-email: Daniel Copley <djcopley@proton.me>
License:                     GNU GENERAL PUBLIC LICENSE
License-File: LICENSE
Classifier: Development Status :: 5 - Production/Stable
Classifier: Environment :: Console
Classifier: Intended Audience :: Developers
Classifier: License :: OSI Approved :: GNU General Public License v3 (GPLv3)
Classifier: Operating System :: MacOS
Classifier: Operating System :: POSIX :: Linux
Classifier: Programming Language :: Python :: 3
Classifier: Programming Language :: Python :: 3.9
Classifier: Programming Language :: Python :: 3.10
Classifier: Programming Language :: Python :: 3.11
Classifier: Programming Language :: Python :: 3.12
Requires-Python: >=3.8
Requires-Dist: hatch~=1.14
